{
  "driver": "GAS",
  "team": "AlphaTauri",
  "session": "Q3",
  "lap_time_s": 101.565,
  "samples": [
    {
      "dist": 0.0,
      "speed": 327.0,
      "time_s": 0.0,
      "x": 950.4,
      "y": -637.4,
      "throttle": 100.0,
      "brake": false,
      "gear": 8
    },
    {
      "dist": 29.9,
      "speed": 328.0,
      "time_s": 0.3,
      "x": 1226.0,
      "y": -523.3,
      "throttle": 100.0,
      "brake": false,
      "gear": 8
    },
    {
      "dist": 59.8,
      "speed": 327.3,
      "time_s": 0.7,
      "x": 1504.0,
      "y": -409.2,
      "throttle": 100.0,
      "brake": false,
      "gear": 8
    },
    {
      "dist": 89.8,
      "speed": 328.0,
      "time_s": 1.0,
      "x": 1779.1,
      "y": -293.2,
      "throttle": 100.0,
      "brake": false,
      "gear": 8
    },
    {
      "dist": 119.7,
      "speed": 329.0,
      "time_s": 1.3,
      "x": 2054.1,
      "y": -177.5,
      "throttle": 100.0,
      "brake": false,
      "gear": 8
    },
    {
      "dist": 149.6,
      "speed": 329.0,
      "time_s": 1.6,
      "x": 2330.3,
      "y": -62.8,
      "throttle": 100.0,
      "brake": false,
      "gear": 8
    },
    {
      "dist": 179.5,
      "speed": 326.7,
      "time_s": 2.0,
      "x": 2606.6,
      "y": 52.8,
      "throttle": 100.0,
      "brake": false,
      "gear": 8
    },
    {
      "dist": 209.4,
      "speed": 307.9,
      "time_s": 2.3,
      "x": 2878.0,
      "y": 172.3,
      "throttle": 11.4,
      "brake": true,
      "gear": 8
    },
    {
      "dist": 239.4,
      "speed": 229.1,
      "time_s": 2.7,
      "x": 3160.1,
      "y": 282.5,
      "throttle": 0.0,
      "brake": true,
      "gear": 7
    },
    {
      "dist": 269.3,
      "speed": 151.2,
      "time_s": 3.4,
      "x": 3451.3,
      "y": 394.2,
      "throttle": 0.0,
      "brake": true,
      "gear": 6
    },
    {
      "dist": 299.2,
      "speed": 125.6,
      "time_s": 4.2,
      "x": 3662.3,
      "y": 572.4,
      "throttle": 0.0,
      "brake": false,
      "gear": 3
    },
    {
      "dist": 329.1,
      "speed": 126.9,
      "time_s": 5.1,
      "x": 3728.3,
      "y": 844.6,
      "throttle": 74.0,
      "brake": false,
      "gear": 3
    },
    {
      "dist": 359.1,
      "speed": 158.8,
      "time_s": 5.8,
      "x": 3625.3,
      "y": 1134.8,
      "throttle": 100.0,
      "brake": false,
      "gear": 3
    },
    {
      "dist": 389.0,
      "speed": 185.0,
      "time_s": 6.4,
      "x": 3500.1,
      "y": 1405.4,
      "throttle": 100.0,
      "brake": false,
      "gear": 4
    },
    {
      "dist": 418.9,
      "speed": 204.5,
      "time_s": 7.0,
      "x": 3386.4,
      "y": 1678.8,
      "throttle": 100.0,
      "brake": false,
      "gear": 4
    },
    {
      "dist": 448.8,
      "speed": 220.0,
      "time_s": 7.5,
      "x": 3264.2,
      "y": 1956.1,
      "throttle": 100.0,
      "brake": false,
      "gear": 5
    },
    {
      "dist": 478.7,
      "speed": 233.0,
      "time_s": 7.9,
      "x": 3140.0,
      "y": 2229.9,
      "throttle": 100.0,
      "brake": false,
      "gear": 5
    },
    {
      "dist": 508.7,
      "speed": 242.3,
      "time_s": 8.4,
      "x": 3020.2,
      "y": 2499.7,
      "throttle": 100.0,
      "brake": false,
      "gear": 6
    },
    {
      "dist": 538.6,
      "speed": 250.1,
      "time_s": 8.8,
      "x": 2896.6,
      "y": 2780.0,
      "throttle": 100.0,
      "brake": false,
      "gear": 6
    },
    {
      "dist": 568.5,
      "speed": 250.1,
      "time_s": 9.2,
      "x": 2773.3,
      "y": 3057.0,
      "throttle": 100.0,
      "brake": true,
      "gear": 6
    },
    {
      "dist": 598.4,
      "speed": 184.2,
      "time_s": 9.8,
      "x": 2648.8,
      "y": 3339.8,
      "throttle": 0.0,
      "brake": true,
      "gear": 6
    },
    {
      "dist": 628.3,
      "speed": 117.8,
      "time_s": 10.6,
      "x": 2512.7,
      "y": 3611.7,
      "throttle": 0.0,
      "brake": true,
      "gear": 3
    },
    {
      "dist": 658.3,
      "speed": 97.7,
      "time_s": 11.6,
      "x": 2269.1,
      "y": 3691.2,
      "throttle": 40.6,
      "brake": false,
      "gear": 3
    },
    {
      "dist": 688.2,
      "speed": 126.3,
      "time_s": 12.6,
      "x": 1970.1,
      "y": 3585.7,
      "throttle": 95.9,
      "brake": false,
      "gear": 3
    },
    {
      "dist": 718.1,
      "speed": 166.5,
      "time_s": 13.3,
      "x": 1695.5,
      "y": 3475.6,
      "throttle": 100.0,
      "brake": false,
      "gear": 3
    },
    {
      "dist": 748.0,
      "speed": 195.1,
      "time_s": 13.8,
      "x": 1422.1,
      "y": 3375.7,
      "throttle": 100.0,
      "brake": false,
      "gear": 4
    },
    {
      "dist": 777.9,
      "speed": 216.5,
      "time_s": 14.4,
      "x": 1147.4,
      "y": 3274.3,
      "throttle": 100.0,
      "brake": false,
      "gear": 5
    },
    {
      "dist": 807.9,
      "speed": 229.6,
      "time_s": 14.8,
      "x": 867.0,
      "y": 3169.6,
      "throttle": 100.0,
      "brake": false,
      "gear": 5
    },
    {
      "dist": 837.8,
      "speed": 243.6,
      "time_s": 15.3,
      "x": 588.7,
      "y": 3065.6,
      "throttle": 100.0,
      "brake": false,
      "gear": 6
    },
    {
      "dist": 867.7,
      "speed": 252.0,
      "time_s": 15.7,
      "x": 307.2,
      "y": 2959.6,
      "throttle": 100.0,
      "brake": false,
      "gear": 6
    },
    {
      "dist": 897.6,
      "speed": 262.8,
      "time_s": 16.1,
      "x": 28.6,
      "y": 2854.6,
      "throttle": 100.0,
      "brake": false,
      "gear": 6
    },
    {
      "dist": 927.6,
      "speed": 270.4,
      "time_s": 16.5,
      "x": -250.5,
      "y": 2751.0,
      "throttle": 100.0,
      "brake": false,
      "gear": 7
    },
    {
      "dist": 957.5,
      "speed": 276.0,
      "time_s": 16.9,
      "x": -530.6,
      "y": 2644.9,
      "throttle": 100.0,
      "brake": false,
      "gear": 7
    },
    {
      "dist": 987.4,
      "speed": 281.4,
      "time_s": 17.3,
      "x": -807.6,
      "y": 2535.9,
      "throttle": 100.0,
      "brake": false,
      "gear": 7
    },
    {
      "dist": 1017.3,
      "speed": 287.7,
      "time_s": 17.7,
      "x": -1081.8,
      "y": 2420.1,
      "throttle": 100.0,
      "brake": false,
      "gear": 7
    },
    {
      "dist": 1047.2,
      "speed": 292.4,
      "time_s": 18.0,
      "x": -1355.5,
      "y": 2300.9,
      "throttle": 100.0,
      "brake": false,
      "gear": 8
    },
    {
      "dist": 1077.2,
      "speed": 296.0,
      "time_s": 18.4,
      "x": -1630.4,
      "y": 2182.8,
      "throttle": 100.0,
      "brake": false,
      "gear": 8
    },
    {
      "dist": 1107.1,
      "speed": 300.4,
      "time_s": 18.8,
      "x": -1903.0,
      "y": 2065.2,
      "throttle": 100.0,
      "brake": false,
      "gear": 8
    },
    {
      "dist": 1137.0,
      "speed": 303.9,
      "time_s": 19.1,
      "x": -2176.1,
      "y": 1947.1,
      "throttle": 100.0,
      "brake": false,
      "gear": 8
    },
    {
      "dist": 1166.9,
      "speed": 305.4,
      "time_s": 19.5,
      "x": -2451.0,
      "y": 1828.3,
      "throttle": 100.0,
      "brake": false,
      "gear": 8
    },
    {
      "dist": 1196.8,
      "speed": 309.1,
      "time_s": 19.8,
      "x": -2725.4,
      "y": 1710.1,
      "throttle": 100.0,
      "brake": false,
      "gear": 8
    },
    {
      "dist": 1226.8,
      "speed": 312.0,
      "time_s": 20.2,
      "x": -2999.4,
      "y": 1591.8,
      "throttle": 100.0,
      "brake": false,
      "gear": 8
    },
    {
      "dist": 1256.7,
      "speed": 313.9,
      "time_s": 20.5,
      "x": -3274.1,
      "y": 1472.9,
      "throttle": 100.0,
      "brake": false,
      "gear": 8
    },
    {
      "dist": 1286.6,
      "speed": 315.4,
      "time_s": 20.9,
      "x": -3547.7,
      "y": 1351.9,
      "throttle": 100.0,
      "brake": false,
      "gear": 8
    },
    {
      "dist": 1316.5,
      "speed": 317.4,
      "time_s": 21.2,
      "x": -3820.8,
      "y": 1229.4,
      "throttle": 100.0,
      "brake": false,
      "gear": 8
    },
    {
      "dist": 1346.4,
      "speed": 319.0,
      "time_s": 21.5,
      "x": -4093.5,
      "y": 1108.3,
      "throttle": 100.0,
      "brake": false,
      "gear": 8
    },
    {
      "dist": 1376.4,
      "speed": 320.4,
      "time_s": 21.9,
      "x": -4366.6,
      "y": 987.3,
      "throttle": 100.0,
      "brake": false,
      "gear": 8
    },
    {
      "dist": 1406.3,
      "speed": 313.5,
      "time_s": 22.2,
      "x": -4641.3,
      "y": 864.4,
      "throttle": 0.0,
      "brake": true,
      "gear": 8
    },
    {
      "dist": 1436.2,
      "speed": 255.9,
      "time_s": 22.6,
      "x": -4922.2,
      "y": 739.9,
      "throttle": 0.0,
      "brake": true,
      "gear": 8
    },
    {
      "dist": 1466.1,
      "speed": 186.0,
      "time_s": 23.1,
      "x": -5204.1,
      "y": 613.9,
      "throttle": 0.0,
      "brake": true,
      "gear": 8
    },
    {
      "dist": 1496.1,
      "speed": 120.2,
      "time_s": 23.9,
      "x": -5474.2,
      "y": 475.0,
      "throttle": 0.0,
      "brake": false,
      "gear": 3
    },
    {
      "dist": 1526.0,
      "speed": 104.2,
      "time_s": 24.9,
      "x": -5596.6,
      "y": 266.0,
      "throttle": 28.0,
      "brake": false,
      "gear": 3
    },
    {
      "dist": 1555.9,
      "speed": 132.5,
      "time_s": 25.8,
      "x": -5470.1,
      "y": -27.7,
      "throttle": 95.0,
      "brake": false,
      "gear": 3
    },
    {
      "dist": 1585.8,
      "speed": 168.1,
      "time_s": 26.5,
      "x": -5346.1,
      "y": -297.0,
      "throttle": 100.0,
      "brake": false,
      "gear": 3
    },
    {
      "dist": 1615.7,
      "speed": 190.2,
      "time_s": 27.1,
      "x": -5254.7,
      "y": -583.7,
      "throttle": 100.0,
      "brake": false,
      "gear": 4
    },
    {
      "dist": 1645.7,
      "speed": 209.4,
      "time_s": 27.6,
      "x": -5144.5,
      "y": -861.1,
      "throttle": 100.0,
      "brake": false,
      "gear": 5
    },
    {
      "dist": 1675.6,
      "speed": 200.1,
      "time_s": 28.1,
      "x": -5015.4,
      "y": -1136.7,
      "throttle": 0.0,
      "brake": true,
      "gear": 5
    },
    {
      "dist": 1705.5,
      "speed": 131.8,
      "time_s": 28.8,
      "x": -4894.3,
      "y": -1418.6,
      "throttle": 0.0,
      "brake": true,
      "gear": 3
    },
    {
      "dist": 1735.4,
      "speed": 101.6,
      "time_s": 29.8,
      "x": -4850.2,
      "y": -1698.7,
      "throttle": 0.0,
      "brake": false,
      "gear": 3
    },
    {
      "dist": 1765.3,
      "speed": 104.0,
      "time_s": 30.9,
      "x": -5044.3,
      "y": -1902.8,
      "throttle": 61.0,
      "brake": false,
      "gear": 3
    },
    {
      "dist": 1795.3,
      "speed": 147.7,
      "time_s": 31.8,
      "x": -5340.7,
      "y": -2014.0,
      "throttle": 100.0,
      "brake": false,
      "gear": 3
    },
    {
      "dist": 1825.2,
      "speed": 177.5,
      "time_s": 32.4,
      "x": -5611.1,
      "y": -2117.8,
      "throttle": 100.0,
      "brake": false,
      "gear": 4
    },
    {
      "dist": 1855.1,
      "speed": 199.2,
      "time_s": 32.9,
      "x": -5881.9,
      "y": -2238.0,
      "throttle": 100.0,
      "brake": false,
      "gear": 4
    },
    {
      "dist": 1885.0,
      "speed": 218.4,
      "time_s": 33.4,
      "x": -6157.3,
      "y": -2353.3,
      "throttle": 100.0,
      "brake": false,
      "gear": 5
    },
    {
      "dist": 1915.0,
      "speed": 231.4,
      "time_s": 33.9,
      "x": -6424.5,
      "y": -2479.7,
      "throttle": 100.0,
      "brake": false,
      "gear": 5
    },
    {
      "dist": 1944.9,
      "speed": 240.0,
      "time_s": 34.4,
      "x": -6683.6,
      "y": -2627.4,
      "throttle": 100.0,
      "brake": false,
      "gear": 5
    },
    {
      "dist": 1974.8,
      "speed": 250.4,
      "time_s": 34.8,
      "x": -6939.5,
      "y": -2782.9,
      "throttle": 100.0,
      "brake": false,
      "gear": 6
    },
    {
      "dist": 2004.7,
      "speed": 233.1,
      "time_s": 35.2,
      "x": -7205.5,
      "y": -2934.2,
      "throttle": 0.0,
      "brake": true,
      "gear": 6
    },
    {
      "dist": 2034.6,
      "speed": 175.4,
      "time_s": 35.8,
      "x": -7461.1,
      "y": -3079.4,
      "throttle": 0.0,
      "brake": true,
      "gear": 4
    },
    {
      "dist": 2064.6,
      "speed": 133.7,
      "time_s": 36.6,
      "x": -7684.3,
      "y": -3276.4,
      "throttle": 0.0,
      "brake": true,
      "gear": 2
    },
    {
      "dist": 2094.5,
      "speed": 110.0,
      "time_s": 37.5,
      "x": -7744.4,
      "y": -3536.6,
      "throttle": 2.2,
      "brake": false,
      "gear": 2
    },
    {
      "dist": 2124.4,
      "speed": 94.1,
      "time_s": 38.5,
      "x": -7609.8,
      "y": -3829.7,
      "throttle": 0.0,
      "brake": true,
      "gear": 2
    },
    {
      "dist": 2154.3,
      "speed": 99.4,
      "time_s": 39.7,
      "x": -7727.3,
      "y": -4071.2,
      "throttle": 63.0,
      "brake": false,
      "gear": 2
    },
    {
      "dist": 2184.2,
      "speed": 139.8,
      "time_s": 40.6,
      "x": -8007.2,
      "y": -4241.1,
      "throttle": 100.0,
      "brake": false,
      "gear": 3
    },
    {
      "dist": 2214.2,
      "speed": 174.9,
      "time_s": 41.2,
      "x": -8265.4,
      "y": -4426.2,
      "throttle": 100.0,
      "brake": false,
      "gear": 3
    },
    {
      "dist": 2244.1,
      "speed": 197.8,
      "time_s": 41.8,
      "x": -8496.9,
      "y": -4610.9,
      "throttle": 100.0,
      "brake": false,
      "gear": 4
    },
    {
      "dist": 2274.0,
      "speed": 213.6,
      "time_s": 42.3,
      "x": -8734.9,
      "y": -4789.0,
      "throttle": 100.0,
      "brake": false,
      "gear": 5
    },
    {
      "dist": 2303.9,
      "speed": 228.6,
      "time_s": 42.8,
      "x": -8971.2,
      "y": -4968.2,
      "throttle": 100.0,
      "brake": false,
      "gear": 5
    },
    {
      "dist": 2333.8,
      "speed": 240.1,
      "time_s": 43.3,
      "x": -9208.8,
      "y": -5149.1,
      "throttle": 100.0,
      "brake": false,
      "gear": 6
    },
    {
      "dist": 2363.8,
      "speed": 250.5,
      "time_s": 43.7,
      "x": -9444.5,
      "y": -5328.2,
      "throttle": 100.0,
      "brake": false,
      "gear": 6
    },
    {
      "dist": 2393.7,
      "speed": 256.9,
      "time_s": 44.1,
      "x": -9681.1,
      "y": -5509.1,
      "throttle": 100.0,
      "brake": false,
      "gear": 6
    },
    {
      "dist": 2423.6,
      "speed": 261.0,
      "time_s": 44.5,
      "x": -9917.6,
      "y": -5688.2,
      "throttle": 100.0,
      "brake": false,
      "gear": 6
    },
    {
      "dist": 2453.5,
      "speed": 212.2,
      "time_s": 45.0,
      "x": -10164.5,
      "y": -5873.8,
      "throttle": 0.0,
      "brake": true,
      "gear": 6
    },
    {
      "dist": 2483.5,
      "speed": 137.9,
      "time_s": 45.7,
      "x": -10402.8,
      "y": -6063.7,
      "throttle": 0.0,
      "brake": true,
      "gear": 3
    },
    {
      "dist": 2513.4,
      "speed": 83.6,
      "time_s": 46.8,
      "x": -10642.9,
      "y": -6226.1,
      "throttle": 0.0,
      "brake": false,
      "gear": 2
    },
    {
      "dist": 2543.3,
      "speed": 86.1,
      "time_s": 48.2,
      "x": -10871.4,
      "y": -6149.9,
      "throttle": 60.8,
      "brake": false,
      "gear": 2
    },
    {
      "dist": 2573.2,
      "speed": 129.9,
      "time_s": 49.1,
      "x": -10985.2,
      "y": -5850.8,
      "throttle": 100.0,
      "brake": false,
      "gear": 2
    },
    {
      "dist": 2603.1,
      "speed": 166.9,
      "time_s": 49.8,
      "x": -11067.7,
      "y": -5567.1,
      "throttle": 100.0,
      "brake": false,
      "gear": 3
    },
    {
      "dist": 2633.1,
      "speed": 191.0,
      "time_s": 50.4,
      "x": -11179.0,
      "y": -5193.1,
      "throttle": 100.0,
      "brake": false,
      "gear": 4
    },
    {
      "dist": 2663.0,
      "speed": 205.1,
      "time_s": 50.9,
      "x": -11265.0,
      "y": -4910.8,
      "throttle": 100.0,
      "brake": true,
      "gear": 4
    },
    {
      "dist": 2692.9,
      "speed": 158.2,
      "time_s": 51.5,
      "x": -11352.3,
      "y": -4616.8,
      "throttle": 0.0,
      "brake": true,
      "gear": 4
    },
    {
      "dist": 2722.8,
      "speed": 123.5,
      "time_s": 52.4,
      "x": -11460.7,
      "y": -4352.8,
      "throttle": 0.0,
      "brake": false,
      "gear": 3
    },
    {
      "dist": 2752.7,
      "speed": 140.0,
      "time_s": 53.2,
      "x": -11741.9,
      "y": -4231.6,
      "throttle": 89.1,
      "brake": false,
      "gear": 3
    },
    {
      "dist": 2782.7,
      "speed": 145.5,
      "time_s": 53.9,
      "x": -12025.9,
      "y": -4181.8,
      "throttle": 0.0,
      "brake": true,
      "gear": 3
    },
    {
      "dist": 2812.6,
      "speed": 108.9,
      "time_s": 54.9,
      "x": -12323.2,
      "y": -4143.7,
      "throttle": 0.0,
      "brake": false,
      "gear": 3
    },
    {
      "dist": 2842.5,
      "speed": 108.2,
      "time_s": 55.9,
      "x": -12524.9,
      "y": -3963.6,
      "throttle": 61.0,
      "brake": false,
      "gear": 3
    },
    {
      "dist": 2872.4,
      "speed": 113.9,
      "time_s": 56.8,
      "x": -12570.4,
      "y": -3654.1,
      "throttle": 0.0,
      "brake": false,
      "gear": 3
    },
    {
      "dist": 2902.3,
      "speed": 116.5,
      "time_s": 57.8,
      "x": -12848.5,
      "y": -3580.0,
      "throttle": 70.2,
      "brake": false,
      "gear": 3
    },
    {
      "dist": 2932.3,
      "speed": 151.8,
      "time_s": 58.6,
      "x": -13147.3,
      "y": -3629.3,
      "throttle": 100.0,
      "brake": false,
      "gear": 3
    },
    {
      "dist": 2962.2,
      "speed": 181.6,
      "time_s": 59.2,
      "x": -13508.5,
      "y": -3761.2,
      "throttle": 100.0,
      "brake": false,
      "gear": 4
    },
    {
      "dist": 2992.1,
      "speed": 200.8,
      "time_s": 59.7,
      "x": -13778.0,
      "y": -3885.4,
      "throttle": 100.0,
      "brake": false,
      "gear": 4
    },
    {
      "dist": 3022.0,
      "speed": 213.0,
      "time_s": 60.3,
      "x": -14053.1,
      "y": -4000.3,
      "throttle": 100.0,
      "brake": false,
      "gear": 5
    },
    {
      "dist": 3052.0,
      "speed": 231.1,
      "time_s": 60.7,
      "x": -14320.5,
      "y": -4127.2,
      "throttle": 100.0,
      "brake": false,
      "gear": 5
    },
    {
      "dist": 3081.9,
      "speed": 241.0,
      "time_s": 61.2,
      "x": -14584.5,
      "y": -4266.0,
      "throttle": 100.0,
      "brake": false,
      "gear": 6
    },
    {
      "dist": 3111.8,
      "speed": 249.9,
      "time_s": 61.6,
      "x": -14851.2,
      "y": -4398.2,
      "throttle": 100.0,
      "brake": false,
      "gear": 6
    },
    {
      "dist": 3141.7,
      "speed": 256.9,
      "time_s": 62.0,
      "x": -15117.1,
      "y": -4534.6,
      "throttle": 100.0,
      "brake": false,
      "gear": 6
    },
    {
      "dist": 3171.6,
      "speed": 264.0,
      "time_s": 62.4,
      "x": -15376.0,
      "y": -4682.2,
      "throttle": 100.0,
      "brake": false,
      "gear": 7
    },
    {
      "dist": 3201.6,
      "speed": 270.5,
      "time_s": 62.8,
      "x": -15633.2,
      "y": -4832.2,
      "throttle": 100.0,
      "brake": false,
      "gear": 7
    },
    {
      "dist": 3231.5,
      "speed": 274.2,
      "time_s": 63.2,
      "x": -15880.9,
      "y": -4970.0,
      "throttle": 100.0,
      "brake": false,
      "gear": 7
    },
    {
      "dist": 3261.4,
      "speed": 276.7,
      "time_s": 63.6,
      "x": -16126.0,
      "y": -5118.5,
      "throttle": 100.0,
      "brake": false,
      "gear": 7
    },
    {
      "dist": 3291.3,
      "speed": 279.3,
      "time_s": 64.0,
      "x": -16308.3,
      "y": -5337.9,
      "throttle": 100.0,
      "brake": false,
      "gear": 7
    },
    {
      "dist": 3321.2,
      "speed": 281.8,
      "time_s": 64.4,
      "x": -16432.1,
      "y": -5623.7,
      "throttle": 100.0,
      "brake": false,
      "gear": 7
    },
    {
      "dist": 3351.2,
      "speed": 284.5,
      "time_s": 64.8,
      "x": -16522.0,
      "y": -5912.7,
      "throttle": 100.0,
      "brake": false,
      "gear": 7
    },
    {
      "dist": 3381.1,
      "speed": 288.1,
      "time_s": 65.2,
      "x": -16605.9,
      "y": -6199.2,
      "throttle": 100.0,
      "brake": false,
      "gear": 8
    },
    {
      "dist": 3411.0,
      "speed": 290.2,
      "time_s": 65.5,
      "x": -16697.1,
      "y": -6483.6,
      "throttle": 100.0,
      "brake": false,
      "gear": 8
    },
    {
      "dist": 3440.9,
      "speed": 292.3,
      "time_s": 65.9,
      "x": -16789.2,
      "y": -6768.8,
      "throttle": 100.0,
      "brake": false,
      "gear": 8
    },
    {
      "dist": 3470.8,
      "speed": 295.3,
      "time_s": 66.3,
      "x": -16863.2,
      "y": -7059.6,
      "throttle": 100.0,
      "brake": false,
      "gear": 8
    },
    {
      "dist": 3500.8,
      "speed": 297.1,
      "time_s": 66.6,
      "x": -16902.5,
      "y": -7355.7,
      "throttle": 100.0,
      "brake": false,
      "gear": 8
    },
    {
      "dist": 3530.7,
      "speed": 298.7,
      "time_s": 67.0,
      "x": -16908.2,
      "y": -7655.6,
      "throttle": 100.0,
      "brake": false,
      "gear": 8
    },
    {
      "dist": 3560.6,
      "speed": 300.2,
      "time_s": 67.3,
      "x": -16888.5,
      "y": -7956.5,
      "throttle": 100.0,
      "brake": false,
      "gear": 8
    },
    {
      "dist": 3590.5,
      "speed": 302.3,
      "time_s": 67.7,
      "x": -16866.7,
      "y": -8254.5,
      "throttle": 100.0,
      "brake": false,
      "gear": 8
    },
    {
      "dist": 3620.5,
      "speed": 284.2,
      "time_s": 68.1,
      "x": -16841.1,
      "y": -8553.8,
      "throttle": 0.0,
      "brake": true,
      "gear": 8
    },
    {
      "dist": 3650.4,
      "speed": 214.1,
      "time_s": 68.5,
      "x": -16829.8,
      "y": -8859.1,
      "throttle": 0.0,
      "brake": true,
      "gear": 8
    },
    {
      "dist": 3680.3,
      "speed": 164.1,
      "time_s": 69.1,
      "x": -16857.3,
      "y": -9171.3,
      "throttle": 0.0,
      "brake": true,
      "gear": 8
    },
    {
      "dist": 3710.2,
      "speed": 110.2,
      "time_s": 70.0,
      "x": -16868.7,
      "y": -9476.4,
      "throttle": 0.0,
      "brake": true,
      "gear": 3
    },
    {
      "dist": 3740.1,
      "speed": 95.1,
      "time_s": 71.1,
      "x": -16693.0,
      "y": -9682.9,
      "throttle": 47.7,
      "brake": false,
      "gear": 3
    },
    {
      "dist": 3770.1,
      "speed": 139.9,
      "time_s": 72.0,
      "x": -16398.3,
      "y": -9825.8,
      "throttle": 100.0,
      "brake": false,
      "gear": 3
    },
    {
      "dist": 3800.0,
      "speed": 175.1,
      "time_s": 72.7,
      "x": -16135.5,
      "y": -9961.7,
      "throttle": 100.0,
      "brake": false,
      "gear": 4
    },
    {
      "dist": 3829.9,
      "speed": 195.9,
      "time_s": 73.2,
      "x": -15869.3,
      "y": -10093.6,
      "throttle": 100.0,
      "brake": false,
      "gear": 4
    },
    {
      "dist": 3859.8,
      "speed": 219.9,
      "time_s": 73.7,
      "x": -15603.1,
      "y": -10227.9,
      "throttle": 100.0,
      "brake": false,
      "gear": 5
    },
    {
      "dist": 3889.7,
      "speed": 233.6,
      "time_s": 74.2,
      "x": -15343.6,
      "y": -10370.8,
      "throttle": 100.0,
      "brake": false,
      "gear": 5
    },
    {
      "dist": 3919.7,
      "speed": 244.7,
      "time_s": 74.7,
      "x": -15087.1,
      "y": -10522.8,
      "throttle": 100.0,
      "brake": false,
      "gear": 6
    },
    {
      "dist": 3949.6,
      "speed": 254.3,
      "time_s": 75.1,
      "x": -14826.1,
      "y": -10666.5,
      "throttle": 100.0,
      "brake": false,
      "gear": 6
    },
    {
      "dist": 3979.5,
      "speed": 260.3,
      "time_s": 75.5,
      "x": -14559.5,
      "y": -10805.8,
      "throttle": 100.0,
      "brake": false,
      "gear": 6
    },
    {
      "dist": 4009.4,
      "speed": 226.2,
      "time_s": 75.9,
      "x": -14294.1,
      "y": -10957.1,
      "throttle": 0.0,
      "brake": true,
      "gear": 6
    },
    {
      "dist": 4039.3,
      "speed": 167.2,
      "time_s": 76.5,
      "x": -14029.3,
      "y": -11089.2,
      "throttle": 0.0,
      "brake": true,
      "gear": 6
    },
    {
      "dist": 4069.3,
      "speed": 130.5,
      "time_s": 77.3,
      "x": -13752.2,
      "y": -11140.8,
      "throttle": 0.0,
      "brake": false,
      "gear": 3
    },
    {
      "dist": 4099.2,
      "speed": 121.2,
      "time_s": 78.2,
      "x": -13515.3,
      "y": -10989.0,
      "throttle": 57.8,
      "brake": false,
      "gear": 3
    },
    {
      "dist": 4129.1,
      "speed": 144.4,
      "time_s": 79.0,
      "x": -13370.5,
      "y": -10713.3,
      "throttle": 88.0,
      "brake": false,
      "gear": 3
    },
    {
      "dist": 4159.0,
      "speed": 177.6,
      "time_s": 79.6,
      "x": -13240.9,
      "y": -10449.4,
      "throttle": 100.0,
      "brake": false,
      "gear": 3
    },
    {
      "dist": 4189.0,
      "speed": 199.3,
      "time_s": 80.2,
      "x": -13123.1,
      "y": -10208.4,
      "throttle": 100.0,
      "brake": false,
      "gear": 4
    },
    {
      "dist": 4218.9,
      "speed": 216.1,
      "time_s": 80.7,
      "x": -12995.0,
      "y": -9946.1,
      "throttle": 100.0,
      "brake": false,
      "gear": 5
    },
    {
      "dist": 4248.8,
      "speed": 230.1,
      "time_s": 81.2,
      "x": -12849.9,
      "y": -9689.0,
      "throttle": 100.0,
      "brake": false,
      "gear": 5
    },
    {
      "dist": 4278.7,
      "speed": 241.5,
      "time_s": 81.6,
      "x": -12686.0,
      "y": -9441.1,
      "throttle": 100.0,
      "brake": false,
      "gear": 6
    },
    {
      "dist": 4308.6,
      "speed": 250.1,
      "time_s": 82.1,
      "x": -12500.2,
      "y": -9210.7,
      "throttle": 100.0,
      "brake": false,
      "gear": 6
    },
    {
      "dist": 4338.6,
      "speed": 257.1,
      "time_s": 82.5,
      "x": -12288.1,
      "y": -8999.4,
      "throttle": 100.0,
      "brake": false,
      "gear": 6
    },
    {
      "dist": 4368.5,
      "speed": 262.9,
      "time_s": 82.9,
      "x": -12063.7,
      "y": -8801.8,
      "throttle": 100.0,
      "brake": false,
      "gear": 7
    },
    {
      "dist": 4398.4,
      "speed": 269.9,
      "time_s": 83.3,
      "x": -11838.7,
      "y": -8607.1,
      "throttle": 100.0,
      "brake": false,
      "gear": 7
    },
    {
      "dist": 4428.3,
      "speed": 273.8,
      "time_s": 83.7,
      "x": -11624.6,
      "y": -8400.2,
      "throttle": 100.0,
      "brake": false,
      "gear": 7
    },
    {
      "dist": 4458.2,
      "speed": 276.9,
      "time_s": 84.1,
      "x": -11424.2,
      "y": -8182.2,
      "throttle": 100.0,
      "brake": false,
      "gear": 7
    },
    {
      "dist": 4488.2,
      "speed": 279.5,
      "time_s": 84.5,
      "x": -11174.5,
      "y": -7949.9,
      "throttle": 100.0,
      "brake": false,
      "gear": 7
    },
    {
      "dist": 4518.1,
      "speed": 281.2,
      "time_s": 84.8,
      "x": -10986.8,
      "y": -7726.9,
      "throttle": 100.0,
      "brake": false,
      "gear": 7
    },
    {
      "dist": 4548.0,
      "speed": 285.7,
      "time_s": 85.2,
      "x": -10857.8,
      "y": -7455.0,
      "throttle": 100.0,
      "brake": false,
      "gear": 7
    },
    {
      "dist": 4577.9,
      "speed": 286.9,
      "time_s": 85.6,
      "x": -10769.8,
      "y": -7163.8,
      "throttle": 100.0,
      "brake": false,
      "gear": 8
    },
    {
      "dist": 4607.9,
      "speed": 287.0,
      "time_s": 86.0,
      "x": -10704.5,
      "y": -6869.0,
      "throttle": 100.0,
      "brake": false,
      "gear": 8
    },
    {
      "dist": 4637.8,
      "speed": 287.5,
      "time_s": 86.4,
      "x": -10635.1,
      "y": -6582.8,
      "throttle": 100.0,
      "brake": false,
      "gear": 8
    },
    {
      "dist": 4667.7,
      "speed": 289.0,
      "time_s": 86.7,
      "x": -10514.2,
      "y": -6324.5,
      "throttle": 100.0,
      "brake": false,
      "gear": 8
    },
    {
      "dist": 4697.6,
      "speed": 289.0,
      "time_s": 87.1,
      "x": -10310.5,
      "y": -6102.5,
      "throttle": 100.0,
      "brake": false,
      "gear": 8
    },
    {
      "dist": 4727.5,
      "speed": 291.0,
      "time_s": 87.5,
      "x": -10062.6,
      "y": -5908.8,
      "throttle": 100.0,
      "brake": false,
      "gear": 8
    },
    {
      "dist": 4757.5,
      "speed": 292.8,
      "time_s": 87.8,
      "x": -9797.8,
      "y": -5718.9,
      "throttle": 100.0,
      "brake": false,
      "gear": 8
    },
    {
      "dist": 4787.4,
      "speed": 295.2,
      "time_s": 88.2,
      "x": -9560.4,
      "y": -5537.1,
      "throttle": 100.0,
      "brake": false,
      "gear": 8
    },
    {
      "dist": 4817.3,
      "speed": 298.9,
      "time_s": 88.6,
      "x": -9324.4,
      "y": -5354.5,
      "throttle": 100.0,
      "brake": false,
      "gear": 8
    },
    {
      "dist": 4847.2,
      "speed": 300.3,
      "time_s": 88.9,
      "x": -9086.1,
      "y": -5173.4,
      "throttle": 100.0,
      "brake": false,
      "gear": 8
    },
    {
      "dist": 4877.1,
      "speed": 302.4,
      "time_s": 89.3,
      "x": -8848.9,
      "y": -4991.9,
      "throttle": 100.0,
      "brake": false,
      "gear": 8
    },
    {
      "dist": 4907.1,
      "speed": 303.2,
      "time_s": 89.6,
      "x": -8610.2,
      "y": -4811.8,
      "throttle": 100.0,
      "brake": false,
      "gear": 8
    },
    {
      "dist": 4937.0,
      "speed": 305.0,
      "time_s": 90.0,
      "x": -8372.9,
      "y": -4630.0,
      "throttle": 100.0,
      "brake": false,
      "gear": 8
    },
    {
      "dist": 4966.9,
      "speed": 306.0,
      "time_s": 90.3,
      "x": -8137.6,
      "y": -4446.8,
      "throttle": 100.0,
      "brake": false,
      "gear": 8
    },
    {
      "dist": 4996.8,
      "speed": 306.0,
      "time_s": 90.7,
      "x": -7893.5,
      "y": -4279.0,
      "throttle": 100.0,
      "brake": false,
      "gear": 8
    },
    {
      "dist": 5026.7,
      "speed": 307.0,
      "time_s": 91.0,
      "x": -7592.6,
      "y": -4118.0,
      "throttle": 100.0,
      "brake": false,
      "gear": 8
    },
    {
      "dist": 5056.7,
      "speed": 307.4,
      "time_s": 91.4,
      "x": -7313.9,
      "y": -4000.2,
      "throttle": 100.0,
      "brake": false,
      "gear": 8
    },
    {
      "dist": 5086.6,
      "speed": 308.0,
      "time_s": 91.7,
      "x": -7034.0,
      "y": -3890.6,
      "throttle": 100.0,
      "brake": false,
      "gear": 8
    },
    {
      "dist": 5116.5,
      "speed": 308.4,
      "time_s": 92.1,
      "x": -6756.1,
      "y": -3779.6,
      "throttle": 100.0,
      "brake": false,
      "gear": 8
    },
    {
      "dist": 5146.4,
      "speed": 308.0,
      "time_s": 92.4,
      "x": -6478.7,
      "y": -3666.7,
      "throttle": 100.0,
      "brake": false,
      "gear": 8
    },
    {
      "dist": 5176.4,
      "speed": 308.0,
      "time_s": 92.8,
      "x": -6200.7,
      "y": -3553.5,
      "throttle": 100.0,
      "brake": false,
      "gear": 8
    },
    {
      "dist": 5206.3,
      "speed": 308.9,
      "time_s": 93.1,
      "x": -5936.9,
      "y": -3445.8,
      "throttle": 100.0,
      "brake": false,
      "gear": 8
    },
    {
      "dist": 5236.2,
      "speed": 310.0,
      "time_s": 93.5,
      "x": -5701.9,
      "y": -3348.3,
      "throttle": 100.0,
      "brake": false,
      "gear": 8
    },
    {
      "dist": 5266.1,
      "speed": 310.6,
      "time_s": 93.8,
      "x": -5421.0,
      "y": -3231.5,
      "throttle": 100.0,
      "brake": false,
      "gear": 8
    },
    {
      "dist": 5296.0,
      "speed": 311.0,
      "time_s": 94.2,
      "x": -5144.9,
      "y": -3117.0,
      "throttle": 100.0,
      "brake": false,
      "gear": 8
    },
    {
      "dist": 5326.0,
      "speed": 312.5,
      "time_s": 94.5,
      "x": -4869.3,
      "y": -3002.4,
      "throttle": 100.0,
      "brake": false,
      "gear": 8
    },
    {
      "dist": 5355.9,
      "speed": 313.0,
      "time_s": 94.9,
      "x": -4594.2,
      "y": -2885.8,
      "throttle": 100.0,
      "brake": false,
      "gear": 8
    },
    {
      "dist": 5385.8,
      "speed": 313.0,
      "time_s": 95.2,
      "x": -4318.5,
      "y": -2769.3,
      "throttle": 100.0,
      "brake": false,
      "gear": 8
    },
    {
      "dist": 5415.7,
      "speed": 313.8,
      "time_s": 95.6,
      "x": -4042.7,
      "y": -2652.2,
      "throttle": 100.0,
      "brake": false,
      "gear": 8
    },
    {
      "dist": 5445.6,
      "speed": 316.2,
      "time_s": 95.9,
      "x": -3766.7,
      "y": -2536.0,
      "throttle": 100.0,
      "brake": false,
      "gear": 8
    },
    {
      "dist": 5475.6,
      "speed": 318.2,
      "time_s": 96.2,
      "x": -3491.9,
      "y": -2419.1,
      "throttle": 100.0,
      "brake": false,
      "gear": 8
    },
    {
      "dist": 5505.5,
      "speed": 320.0,
      "time_s": 96.6,
      "x": -3216.4,
      "y": -2302.8,
      "throttle": 100.0,
      "brake": false,
      "gear": 8
    },
    {
      "dist": 5535.4,
      "speed": 321.4,
      "time_s": 96.9,
      "x": -2941.2,
      "y": -2186.9,
      "throttle": 100.0,
      "brake": false,
      "gear": 8
    },
    {
      "dist": 5565.3,
      "speed": 322.0,
      "time_s": 97.3,
      "x": -2666.2,
      "y": -2069.9,
      "throttle": 100.0,
      "brake": false,
      "gear": 8
    },
    {
      "dist": 5595.2,
      "speed": 323.2,
      "time_s": 97.6,
      "x": -2391.4,
      "y": -1953.1,
      "throttle": 100.0,
      "brake": false,
      "gear": 8
    },
    {
      "dist": 5625.2,
      "speed": 324.0,
      "time_s": 97.9,
      "x": -2115.6,
      "y": -1838.2,
      "throttle": 100.0,
      "brake": false,
      "gear": 8
    },
    {
      "dist": 5655.1,
      "speed": 324.8,
      "time_s": 98.2,
      "x": -1838.1,
      "y": -1726.7,
      "throttle": 100.0,
      "brake": false,
      "gear": 8
    },
    {
      "dist": 5685.0,
      "speed": 325.0,
      "time_s": 98.6,
      "x": -1558.1,
      "y": -1620.5,
      "throttle": 100.0,
      "brake": false,
      "gear": 8
    },
    {
      "dist": 5714.9,
      "speed": 324.3,
      "time_s": 98.9,
      "x": -1277.9,
      "y": -1516.7,
      "throttle": 100.0,
      "brake": false,
      "gear": 8
    },
    {
      "dist": 5744.9,
      "speed": 323.1,
      "time_s": 99.2,
      "x": -997.0,
      "y": -1411.3,
      "throttle": 100.0,
      "brake": false,
      "gear": 8
    },
    {
      "dist": 5774.8,
      "speed": 323.5,
      "time_s": 99.6,
      "x": -692.1,
      "y": -1297.2,
      "throttle": 100.0,
      "brake": false,
      "gear": 8
    },
    {
      "dist": 5804.7,
      "speed": 323.7,
      "time_s": 99.9,
      "x": -398.7,
      "y": -1187.8,
      "throttle": 100.0,
      "brake": false,
      "gear": 8
    },
    {
      "dist": 5834.6,
      "speed": 324.0,
      "time_s": 100.2,
      "x": -118.4,
      "y": -1083.4,
      "throttle": 100.0,
      "brake": false,
      "gear": 8
    },
    {
      "dist": 5864.5,
      "speed": 324.5,
      "time_s": 100.6,
      "x": 158.8,
      "y": -973.6,
      "throttle": 100.0,
      "brake": false,
      "gear": 8
    },
    {
      "dist": 5894.5,
      "speed": 325.9,
      "time_s": 100.9,
      "x": 435.9,
      "y": -855.7,
      "throttle": 100.0,
      "brake": false,
      "gear": 8
    },
    {
      "dist": 5924.4,
      "speed": 327.0,
      "time_s": 101.2,
      "x": 674.0,
      "y": -754.2,
      "throttle": 100.0,
      "brake": false,
      "gear": 8
    },
    {
      "dist": 5954.3,
      "speed": 327.6,
      "time_s": 101.6,
      "x": 947.6,
      "y": -639.3,
      "throttle": 100.0,
      "brake": false,
      "gear": 8
    }
  ]
}